Metadata-Version: 1.1
Name: aws-lambda-pyauthlib
Version: 0.2.2
Summary: A python helper library for AWS API Gateway Custom Authorizers
Home-page: https://github.com/oharaandrew314/aws-lambda-pyauthlib/
Author: Andrew O'Hara
Author-email: andrew@andrewohara.io
License: MIT
Platform: UNKNOWN
Classifier: Development Status :: 3 - Alpha
Classifier: Intended Audience :: Developers
Classifier: License :: OSI Approved :: MIT License
Classifier: Operating System :: OS Independent
Classifier: Natural Language :: English
Classifier: Programming Language :: Python
Classifier: Programming Language :: Python :: 2
Classifier: Programming Language :: Python :: 2.7
Classifier: Programming Language :: Python :: 3
Classifier: Programming Language :: Python :: 3.6
